autopypath/__init__.py
autopypath/_context.py
autopypath/_defaults.py
autopypath/_exceptions.py
autopypath/_load_strategy.py
autopypath/_log.py
autopypath/_marker_type.py
autopypath/_meta.py
autopypath/_path_resolution.py
autopypath/_typing.py
autopypath/_validate.py
autopypath/debug.py
autopypath/py.typed
autopypath/_config_py_path/__init__.py
autopypath/_config_py_path/_config_py_path.py
autopypath/_config_py_path/_config/__init__.py
autopypath/_config_py_path/_config/_autopypath.py
autopypath/_config_py_path/_config/_config.py
autopypath/_config_py_path/_config/_default.py
autopypath/_config_py_path/_config/_manual.py
autopypath/_config_py_path/_config/_pyproject.py
autopypath/_config_py_path/_config/_toml.py
autopypath/_doc_utils/__init__.py
autopypath/_doc_utils/_enum_docstrings.py
autopypath/_types/__init__.py
autopypath/_types/_no_path.py
autopypath/custom/__init__.py
autopypath-1.0.1.dist-info/METADATA
autopypath-1.0.1.dist-info/WHEEL
autopypath-1.0.1.dist-info/licenses/LICENSE
autopypath-1.0.1.dist-info/RECORD
