Metadata-Version: 2.4
Name: autopypath
Version: 1.0.1
Summary: Automatic path management for testing and development.
Project-URL: Homepage, https://github.com/JerilynFranz/python-autopypath
Project-URL: Documentation, https://python-autopypath.readthedocs.io/en/latest/
Project-URL: Repository, https://github.com/JerilynFranz/python-autopypath.git
Project-URL: Issues, https://github.com/JerilynFranz/python-autopypath/issues
Project-URL: Changelog, https://github.com/JerilynFranz/python-autopypath/blob/main/CHANGELOG.rst
Author-email: Jerilyn Franz <opensource@snowhare.com>
Maintainer-email: Jerilyn Franz <opensource@snowhare.com>
License-File: LICENSE
Keywords: PYTHONPATH,automation,configuration,development,dynamic import,environment,import,path management,runtime,sys.path,testing,tooling
Classifier: Development Status :: 5 - Production/Stable
Classifier: Intended Audience :: Developers
Classifier: License :: OSI Approved :: Apache Software License
Classifier: Operating System :: MacOS :: MacOS X
Classifier: Operating System :: Microsoft :: Windows
Classifier: Operating System :: OS Independent
Classifier: Operating System :: POSIX :: Linux
Classifier: Programming Language :: Python
Classifier: Programming Language :: Python :: 3
Classifier: Programming Language :: Python :: 3.9
Classifier: Programming Language :: Python :: 3.10
Classifier: Programming Language :: Python :: 3.11
Classifier: Programming Language :: Python :: 3.12
Classifier: Programming Language :: Python :: 3.13
Classifier: Programming Language :: Python :: 3.14
Classifier: Programming Language :: Python :: Implementation :: CPython
Classifier: Programming Language :: Python :: Implementation :: PyPy
Classifier: Topic :: Software Development :: Libraries
Classifier: Topic :: Software Development :: Libraries :: Python Modules
Classifier: Topic :: Software Development :: Testing
Classifier: Topic :: Utilities
Requires-Python: >=3.9
Requires-Dist: tomli
Requires-Dist: typing-extensions>=3.10.0.0
